[
  {
    "id": "registrationSummary.overallActions.registrationHome",
    "extensionPointId": "registrationSummary.overallActions",
    "type": "link",
    "label": "rwandaemr.registration.home",
    "url": "registrationapp/findPatient.page?appId=rwandaemr.registerPatient",
    "order": 1
  },
  {
    "id": "registrationSummary.overallActions.insurancePolicies",
    "extensionPointId": "registrationSummary.overallActions",
    "type": "link",
    "label": "rwandaemr.insurancePolicies.manage",
    "url": "rwandaemr/patient/insurancePolicies.page?patientId={{patient.patientId}}&returnUrl=registrationSummary",
    "order": 2
  },
  {
    "id": "registrationSummary.overallActions.realTimeRegistration",
    "extensionPointId": "registrationSummary.overallActions",
    "type": "link",
    "label": "rwandaemr.startVisit",
    "url": "htmlformentryui/htmlform/enterHtmlFormWithStandardUi.page?patientId={{patient.uuid}}&createVisit=true&definitionUiResource=file:configuration/htmlforms/registration.xml",
    "order": 3,
    "require": "visit == null || !visit.encounters || !some(visit.encounters, (function(encounter) { return encounter.encounterType.uuid === 'cfe614d5-fa7e-4919-b76b-a66117f57e4c'; } ))"
  },
  {
    "id": "registrationSummary.overallActions.visitDashboard",
    "extensionPointId": "registrationSummary.overallActions",
    "type": "link",
    "label": "rwandaemr.visitDashboard.view",
    "url": "coreapps/patientdashboard/patientDashboard.page?patientId={{patient.uuid}}",
    "order": 5
  },
  {
    "id": "registrationSummary.overallActions.enterPastVisit",
    "extensionPointId": "registrationSummary.overallActions",
    "type": "script",
    "label": "rwandaemr.startVisit.retrospective",
    "script": "visit.showRetrospectiveVisitCreationDialog()",
    "order": 6,
    "requiredPrivilege": "Task: coreapps.createRetrospectiveVisit"
  },
  {
    "id": "registrationSummary.overallActions.clinicalDashboard",
    "extensionPointId": "registrationSummary.overallActions",
    "type": "link",
    "label": "rwandaemr.clinicalDashboard.view",
    "url": "coreapps/clinicianfacing/patient.page?patientId={{patient.uuid}}&appId=rwandaemr.registerPatient",
    "order": 7
  },
  {
    "id": "registrationSummary.overallActions.privateAdmission",
    "extensionPointId": "registrationSummary.overallActions",
    "type": "link",
    "label": "Private Admission",
    "url": "module/mohbilling/admissionSearch.form",
    "order": 1
  }
]

